pik_utils/__init__.py
pik_utils-1.0.0.dist-info/METADATA
pik_utils-1.0.0.dist-info/WHEEL
pik_utils-1.0.0.dist-info/top_level.txt
pik_utils-1.0.0.dist-info/RECORD
