Metadata-Version: 2.1
Name: pik-utils
Version: 1.0.0
Summary: Utils ofr pik
Home-page: UNKNOWN
Author: GigaAlex
Author-email: nick.faltermeier@gmx.de
License: UNKNOWN
Keywords: python
Platform: UNKNOWN
Classifier: Operating System :: Microsoft :: Windows
